{
    "deps": [
        "/packing/geometric/bp-ks-sp",
        "/packing/geometric/nfdh/algo",
        "/packing/geometric/nfdh/bp-small"
    ],
    "deps_status": "incomplete",
    "metadata": {
        "type": "theorem",
        "title": "PTAS for 2D geometric density-restricted knapsack",
        "description": "When the profit-to-area ratio is upper-bounded and lower-bounded by a constant, then there is a PTAS for the knapsack problem."
    },
    "document": [
        {
            "type": "include",
            "path": "/packing/geometric/2d-dr-ks-ptas.md"
        },
        {
            "type": "include",
            "path": "/bib/packing/bansal2009structural.html"
        }
    ]
}
