{
    "deps": [
        "/graph-theory/dfs/edge-classification",
        "/graph-theory/dfs/white-path-theorem"
    ],
    "metadata": {
        "type": "theorem",
        "title": "DFS: Edge classification in undirected graphs",
        "description": "In an undirected graph, one of (u, v) and (v, u) is a back edge and the other is either a tree edge or a forward edge."
    },
    "document": {
        "type": "include",
        "path": "/graph-theory/dfs/undirected-edge-classification.md"
    }
}
